[
  {
    "path": "dist/motion.min.css",
    "limit": "257336 B",
    "name": "dist/motion.min.css",
    "gzip": false,
    "brotli": false
  },
  {
    "path": "dist/motion.css",
    "limit": "388348 B",
    "name": "dist/motion.css",
    "gzip": false,
    "brotli": false
  },
  {
    "path": "dist/sds-scroll.min.js",
    "limit": "1366 B",
    "name": "dist/sds-scroll.min.js",
    "gzip": false,
    "brotli": false
  },
  {
    "path": "dist/motion-interactive.min.js",
    "limit": "7436 B",
    "name": "dist/motion-interactive.min.js",
    "gzip": false,
    "brotli": false
  },
  {
    "path": "dist/categories/core.min.css",
    "limit": "3535 B",
    "name": "dist/categories/core.min.css",
    "gzip": false,
    "brotli": false
  },
  {
    "path": "dist/categories/text.min.css",
    "limit": "48311 B",
    "name": "dist/categories/text.min.css",
    "gzip": false,
    "brotli": false
  },
  {
    "path": "dist/categories/buttons.min.css",
    "limit": "52294 B",
    "name": "dist/categories/buttons.min.css",
    "gzip": false,
    "brotli": false
  },
  {
    "path": "dist/categories/inputs.min.css",
    "limit": "50050 B",
    "name": "dist/categories/inputs.min.css",
    "gzip": false,
    "brotli": false
  },
  {
    "path": "dist/categories/cards.min.css",
    "limit": "42172 B",
    "name": "dist/categories/cards.min.css",
    "gzip": false,
    "brotli": false
  },
  {
    "path": "dist/categories/loaders.min.css",
    "limit": "52343 B",
    "name": "dist/categories/loaders.min.css",
    "gzip": false,
    "brotli": false
  },
  {
    "path": "dist/categories/scroll.min.css",
    "limit": "35791 B",
    "name": "dist/categories/scroll.min.css",
    "gzip": false,
    "brotli": false
  },
  {
    "path": "packages/react/dist/index.js",
    "limit": "91479 B",
    "name": "packages/react/dist/index.js",
    "gzip": false,
    "brotli": false
  },
  {
    "path": "packages/elements/dist/index.global.js",
    "limit": "73941 B",
    "name": "packages/elements/dist/index.global.js",
    "gzip": false,
    "brotli": false
  },
  {
    "path": "packages/tailwind/dist/sds-motion.css",
    "limit": "593464 B",
    "name": "packages/tailwind/dist/sds-motion.css",
    "gzip": false,
    "brotli": false
  }
]
